bloodline/__init__.py
bloodline/apply.py
bloodline/constants.py
bloodline/context.py
bloodline/erd.py
bloodline/lineage.py
bloodline/pandas_hooks.py
bloodline/source.py
bloodline/tracking.py
bloodline/utils.py
bloodline-0.2.2.dist-info/licenses/LICENSE
bloodline-0.2.2.dist-info/METADATA
bloodline-0.2.2.dist-info/WHEEL
bloodline-0.2.2.dist-info/top_level.txt
bloodline-0.2.2.dist-info/RECORD
