Metadata-Version: 2.4
Name: bloodline
Version: 0.2.2
Summary: 🧛 Row-level data lineage tracking
Author-email: Alexis Cruveiller <alexis@carbonfact.com>, Max Halford <max@carbonfact.com>
Maintainer-email: Alexis Cruveiller <alexis@carbonfact.com>, Max Halford <max@carbonfact.com>
License: Apache-2.0
Requires-Python: >=3.11
License-File: LICENSE
Requires-Dist: pandas>=2.3.3
Requires-Dist: loguru>=0.7.2
Dynamic: license-file
